{
    "_config_name": "block.custom.backdrop_live",
    "delta": "backdrop_live",
    "info": "Backdrop LIVE",
    "title": "Upcoming Events",
    "description": "Promote Backdrop LIVE",
    "body": {
        "value": "<p>\r\n    <strong>Stanford Web Camp</strong><br>\r\n    <a href=\"https://webcamp.stanford.edu/session/backdropcms-in-higher-ed-stanford-and-penn-state-case-studies\" target=\"_blank\"><strong>Backdrop CMS in Higher Ed: Stanford and Penn State case studies</strong></a><br>\r\n    May 2, 2024 1-1:45 PM PDT\r\n</p>\r\n<div class=\"views-field views-field-field-session-date\">\r\n    <p>\r\n        <strong>Backdrop LIVE</strong><br>\r\n        Save the date: Oct 10th &amp; 11th, 2024\r\n    </p>\r\n    <p>\r\n        <strong>Backdrop office hours</strong><br>\r\n        Every Wednesday&nbsp;19:00 - 21:00 UTC\r\n    </p>\r\n</div>",
        "format": "filtered_html"
    },
    "default_langcode": "und"
}
