{
    "_config_name": "block.custom.books",
    "delta": "books",
    "info": "Backdrop Books",
    "title": "Books",
    "body": {
        "value": "<p>Two new books by Todd Tomlinson, author of “Pro Drupal 7 Development”:</p>\r\n\r\n<a href=\"https://www.amazon.com/Beginning-Backdrop-CMS-Todd-Tomlinson/dp/1484219694\"><img src=\"https://backdropcms.org/files/beginningbackdropcms_1.jpg\" /></a><br/>\r\n“<a href=\"https://www.amazon.com/Beginning-Backdrop-CMS-Todd-Tomlinson/dp/1484219694\">Beginning Backdrop CMS</a>”\r\n\r\n<a href=\"http://www.amazon.com/Migrating-Drupal-Backdrop-Todd-Tomlinson/dp/1484217594\"><img src=\"https://backdropcms.org/files/inline-images/book.jpg\" /></a><br/>\r\n“<a href=\"http://www.amazon.com/Migrating-Drupal-Backdrop-Todd-Tomlinson/dp/1484217594\">Migrating from Drupal to Backdrop</a>”",
        "format": "full_html"
    },
    "description": "A reusable custom block."
}
